unieai_excel_mcp/__init__.py
unieai_excel_mcp/__main__.py
unieai_excel_mcp/tools/write_excel.py
unieai_excel_mcp-0.1.10.dist-info/METADATA
unieai_excel_mcp-0.1.10.dist-info/WHEEL
unieai_excel_mcp-0.1.10.dist-info/entry_points.txt
unieai_excel_mcp-0.1.10.dist-info/top_level.txt
unieai_excel_mcp-0.1.10.dist-info/RECORD
