Metadata-Version: 2.4
Name: unieai_excel_mcp
Version: 0.1.10
Summary: Excel 填充模板工具（支援 {{key}} 樣板）
Author-email: Evan <you@example.com>
Requires-Dist: openpyxl
Requires-Dist: mcp
Requires-Dist: typer
Requires-Dist: fastmcp>=0.1.0
